Metadata-Version: 2.1
Name: calici-pk
Version: 0.0.1
Summary: this is a trial package used for calculation.
Home-page: UNKNOWN
Author: pavankumar.s
Author-email: pavankumar.sa02@gmail.com
License: MIT
Platform: UNKNOWN
License-File: Licence.txt
